pyprojectsort/__init__.py
pyprojectsort/__main__.py
pyprojectsort/__version__.py
pyprojectsort/main.py
pyprojectsort-0.4.0.dist-info/entry_points.txt
pyprojectsort-0.4.0.dist-info/LICENSE
pyprojectsort-0.4.0.dist-info/WHEEL
pyprojectsort-0.4.0.dist-info/METADATA
pyprojectsort-0.4.0.dist-info/RECORD
