Metadata-Version: 2.3
Name: pyprojectsort
Version: 0.4.0
Summary: Formatter for pyproject.toml files
Keywords: formatter,pyproject
Author: Kieran Ryan
Requires-Python: >=3.7
Classifier: Environment :: Console
Classifier: Intended Audience :: Developers
Classifier: License :: OSI Approved :: MIT License
Classifier: Operating System :: OS Independent
Classifier: Programming Language :: Python :: 3 :: Only
Classifier: Programming Language :: Python :: 3.7
Classifier: Programming Language :: Python :: 3.8
Classifier: Programming Language :: Python :: 3.9
Classifier: Programming Language :: Python :: 3.10
Classifier: Programming Language :: Python :: 3.11
Classifier: Programming Language :: Python :: 3.12
Classifier: Programming Language :: Python :: 3.13
Classifier: Topic :: Software Development :: Quality Assurance
Requires-Dist: natsort>=8.4.0,<9
Requires-Dist: tomli-w>=1.0.0
Requires-Dist: tomli>=2.0.1,<3
Project-URL: Changelog, https://github.com/kieran-ryan/pyprojectsort/blob/main/CHANGELOG.md
Project-URL: Documentation, https://kieran-ryan.github.io/pyprojectsort
Project-URL: Source, https://github.com/kieran-ryan/pyprojectsort
Project-URL: Tracker, https://github.com/kieran-ryan/pyprojectsort/issues
